ketter/__init__.py
ketter/__main__.py
ketter/arguments.py
ketter/colour.py
ketter/downloader.py
ketter/errors.py
ketter/utils.py
ketter-1.3.3.dist-info/LICENSE
ketter-1.3.3.dist-info/METADATA
ketter-1.3.3.dist-info/WHEEL
ketter-1.3.3.dist-info/entry_points.txt
ketter-1.3.3.dist-info/top_level.txt
ketter-1.3.3.dist-info/RECORD
