Metadata-Version: 2.1
Name: ketter
Version: 1.3.3
Summary: Asynchronous HTTP downloader
Author-email: Kelsey Mwongeli <kelseykm.git@gmail.com>
Project-URL: repository, https://github.com/kelseykm/ketter
Project-URL: changelog, https://github.com/kelseykm/ketter/blob/main/CHANGELOG.md
Keywords: downloader,asynchronous-downloader
License-File: LICENSE
Requires-Dist: aiofiles
Requires-Dist: aiohttp
Requires-Dist: tqdm
